LICENSE
MANIFEST.in
setup.py
gatekeeper/__init__.py
gatekeeper/app.py
gatekeeper/exceptions.py
gatekeeper/test_client.py
gatekeeper.egg-info/PKG-INFO
gatekeeper.egg-info/SOURCES.txt
gatekeeper.egg-info/dependency_links.txt
gatekeeper.egg-info/entry_points.txt
gatekeeper.egg-info/top_level.txt
gatekeeper/endpoints/endpoint.py
gatekeeper/endpoints/html_endpoint.py
gatekeeper/endpoints/json_endpoint.py
gatekeeper/requests/__init__.py
gatekeeper/requests/html_request.py
gatekeeper/requests/json_request.py
gatekeeper/requests/request.py
gatekeeper/requests/uploaded_file.py
gatekeeper/responses/__init__.py
gatekeeper/responses/html_response.py
gatekeeper/responses/json_response.py
gatekeeper/responses/response.py