Metadata-Version: 1.0
Name: gatekeeper
Version: 0.0.0
Summary: Python library handle incoming HTTP requests.
Home-page: https://github.com/hugollm/gatekeeper
Author: Hugo Leonardo Leão Mota
Author-email: hugo.txt@gmail.com
License: MIT
Keywords: gatekeeper http routing wsgi endpoint request response
Platform: UNKNOWN
